Metadata-Version: 2.1
Name: hyper-prompt
Version: 1.1.1
Summary: Highly Customize-able prompt for your shell
Home-page: https://github.com/artbycrunk/hyper-prompt
Author: Savio Fernandes
Author-email: savio@saviof.com
License: MIT
Download-URL: https://github.com/artbycrunk/hyper-prompt/archive/1.1.0.tar.gz
Keywords: prompts,shell,bash,zsh
Platform: UNKNOWN
Classifier: Development Status :: 5 - Production/Stable
Classifier: License :: OSI Approved :: MIT License
Classifier: Programming Language :: Python :: 3
Classifier: Programming Language :: Python :: 3.3
Classifier: Programming Language :: Python :: 3.4
Classifier: Programming Language :: Python :: 3.5
Classifier: Programming Language :: Python :: 3.6
Classifier: Programming Language :: Python :: 3.7
Provides-Extra: develop
